bridge_sim/__init__.py
bridge_sim/bridges/__init__.py
bridge_sim/bridges/bridge_705.py
bridge_sim/configs/__init__.py
bridge_sim/crack.py
bridge_sim/creep/__init__.py
bridge_sim/internal/__init__.py
bridge_sim/internal/cli.py
bridge_sim/internal/make/__init__.py
bridge_sim/internal/make/asphalt.py
bridge_sim/internal/make/crack.py
bridge_sim/internal/make/crack_question.py
bridge_sim/internal/make/creep.py
bridge_sim/internal/make/paramselect.py
bridge_sim/internal/make/plot/contour/__init__.py
bridge_sim/internal/make/plot/geometry.py
bridge_sim/internal/make/plot/vehicle.py
bridge_sim/internal/make/plot/verification.py
bridge_sim/internal/make/ps_question.py
bridge_sim/internal/make/shrinkage.py
bridge_sim/internal/make/strain.py
bridge_sim/internal/make/temperature.py
bridge_sim/internal/make/traffic.py
bridge_sim/internal/make/uls.py
bridge_sim/internal/make/validate.py
bridge_sim/internal/make/validation.py
bridge_sim/internal/plot/__init__.py
bridge_sim/internal/plot/contour.py
bridge_sim/internal/plot/geometry/__init__.py
bridge_sim/internal/plot/geometry/angles.py
bridge_sim/internal/plot/geometry/compass-rose.png
bridge_sim/internal/plot/geometry/node.py
bridge_sim/internal/plot/geometry/shell.py
bridge_sim/internal/plot/responses.py
bridge_sim/internal/plot/temperature.py
bridge_sim/internal/plot/validation.py
bridge_sim/internal/plot/vehicle.py
bridge_sim/internal/plot/vehicles.py
bridge_sim/internal/validate/__init__.py
bridge_sim/model/__init__.py
bridge_sim/plot/__init__.py
bridge_sim/plot/animate.py
bridge_sim/plot/compass-rose.png
bridge_sim/plot/util.py
bridge_sim/shrinkage/__init__.py
bridge_sim/sim/__init__.py
bridge_sim/sim/build/__init__.py
bridge_sim/sim/build/deck.py
bridge_sim/sim/build/piers.py
bridge_sim/sim/crack.py
bridge_sim/sim/model/__init__.py
bridge_sim/sim/responses/__init__.py
bridge_sim/sim/responses/without.py
bridge_sim/sim/run/__init__.py
bridge_sim/sim/run/opensees/__init__.py
bridge_sim/sim/run/opensees/build/__init__.py
bridge_sim-0.0.8.9.dist-info/LICENSE
bridge_sim-0.0.8.9.dist-info/WHEEL
bridge_sim-0.0.8.9.dist-info/METADATA
bridge_sim-0.0.8.9.dist-info/RECORD
