Metadata-Version: 2.1
Name: bridge-sim
Version: 0.0.8.9
Summary: A Python library for concrete slab bridge simulation
Home-page: https://github.com/jerbaroo/bridge-sim
Author: Jeremy Barisch-Rooney
Author-email: jerbaroo.work@pm.me
Requires-Python: >=3.8
Classifier: Programming Language :: Python :: 3
Classifier: Programming Language :: Python :: 3.8
Classifier: Programming Language :: Python :: 3.9
Requires-Dist: click (==7.1.2)
Requires-Dist: colorama (==0.4.3)
Requires-Dist: findup (==0.3.0)
Requires-Dist: matplotlib (==3.2.1)
Requires-Dist: numba (==0.50.0rc1)
Requires-Dist: numpy (==1.19.0rc2)
Requires-Dist: pandas (==1.0.4)
Requires-Dist: pathos (==0.2.5)
Requires-Dist: portalocker (==1.7.0)
Requires-Dist: scipy (==1.5.0rc1)
Requires-Dist: sklearn (==0.0)
Requires-Dist: termcolor (==1.1.0)
Project-URL: Documentation, https://github.com/jerbaroo/bridge-sim/blob/master/README.org#concrete-slab-bridge-simulation
Project-URL: Repository, https://github.com/jerbaroo/bridge-sim
